openidc_client/__init__.py
openidc_client/release.py
openidc_client/requestsauth.py
solidclient/__init__.py
solidclient/solid_client.py
solidclient/utils/__init__.py
solidclient/utils/utils.py
solidclient-0.1.10.dist-info/LICENSE
solidclient-0.1.10.dist-info/METADATA
solidclient-0.1.10.dist-info/WHEEL
solidclient-0.1.10.dist-info/top_level.txt
solidclient-0.1.10.dist-info/RECORD
