Metadata-Version: 2.1
Name: solidclient
Version: 0.1.10
Summary: Solid Client in Python (https://solidproject.org/)
Home-page: https://gitlab.com/arbetsformedlingen/individdata/oak/python-solid-client
Author: Max Dzyuba
Author-email: max.dzyuba@arbetsformedlingen.se
License: MIT
Project-URL: Bug Tracker, https://gitlab.com/arbetsformedlingen/individdata/oak/python-solid-client/-/issues
Keywords: solid,client,oidc,dpop
Classifier: Programming Language :: Python :: 3
Classifier: License :: OSI Approved :: MIT License
Classifier: Operating System :: OS Independent
Classifier: Topic :: System :: Systems Administration
Classifier: Topic :: Utilities
Requires-Python: >=3.6
License-File: LICENSE
Requires-Dist: requests (==2.25.1)
Requires-Dist: jwcrypto (==1.4)
Requires-Dist: solid-file (==0.2.1)
Requires-Dist: oic (==1.3.0)
Requires-Dist: cached-property (==1.5.2)
